nnstacking/__init__.py
nnstacking/linear_stack.py
nnstacking/nne.py
nnstacking/nnpredict.py
nnstacking-0.0.1.dist-info/LICENSE
nnstacking-0.0.1.dist-info/METADATA
nnstacking-0.0.1.dist-info/WHEEL
nnstacking-0.0.1.dist-info/top_level.txt
nnstacking-0.0.1.dist-info/RECORD
