Metadata-Version: 2.1
Name: nnstacking
Version: 0.0.1
Summary: Emsembler of predictors using neural networks
Home-page: UNKNOWN
Author: Marco Inacio, Victor Coscrato
Author-email: pythonpackages@marcoinacio.com, vcoscrato@gmail.com
License: GPL3
Keywords: neural networks,predictors
Platform: UNKNOWN
Requires-Dist: numpy
Requires-Dist: scikit-learn
